[
  {
    "Index": 0,
    "ID": "impact potential/acid/kg so2-eq",
    "Name": "Acid Rain",
    "Code": "ACID",
    "Unit": "kg SO2-eq",
    "Group": "Impact Potential",
    "SimpleUnit": "Kilograms Sulphur Dioxide (SO2)",
    "SimpleName": "Acid Rain",
    "Set": "Water"
  },
  {
    "Index": 1,
    "ID": "impact potential/eutr/kg n-eq",
    "Name": "Eutrophication",
    "Code": "EUTR",
    "Unit": "kg N-eq",
    "Group": "Impact Potential",
    "SimpleUnit": "Kilograms Nitrogen (N)",
    "SimpleName": "Water Eutrophication",
    "Set": "Water"
  },
  {
    "Index": 2,
    "ID": "impact potential/etox/ctue",
    "Name": "Freshwater Aquatic Ecotoxicity",
    "Code": "ETOX",
    "Unit": "CTUe",
    "Group": "Impact Potential",
    "SimpleUnit": "Comparative Toxic Unit for Ecosystem (CTUe)",
    "SimpleName": "Freshwater Ecotoxicity",
    "Set": "Water"
  },
  {
    "Index": 3,
    "ID": "impact potential/ghg/kg co2-eq",
    "Name": "Greenhouse Gases",
    "Code": "GHG",
    "Unit": "kg CO2-eq",
    "Group": "Impact Potential",
    "SimpleUnit": "Kilograms Carbon Dioxide (CO2)",
    "SimpleName": "Greenhouse Gases",
    "Set": "Air"
  },
  {
    "Index": 4,
    "ID": "impact potential/mghg/kg co2-eq",
    "Name": "Major Greenhouse Gases",
    "Code": "MGHG",
    "Unit": "kg CO2-eq",
    "Group": "Impact Potential",
    "SimpleUnit": "Kilograms Carbon Dioxide (CO2)",
    "SimpleName": "Major Greenhouse Gases",
    "Set": "Air"
  },
  {
    "Index": 5,
    "ID": "impact potential/oghg/kg co2-eq",
    "Name": "Other Greenhouse Gases",
    "Code": "OGHG",
    "Unit": "kg CO2-eq",
    "Group": "Impact Potential",
    "SimpleUnit": "Kilograms Carbon Dioxide (CO2)",
    "SimpleName": "Other Greenhouse Gases",
    "Set": "Air"
  },
  {
    "Index": 6,
    "ID": "impact potential/hcan/ctuh",
    "Name": "Human Health - Cancer",
    "Code": "HCAN",
    "Unit": "CTUh",
    "Group": "Impact Potential",
    "SimpleUnit": "Comparative Toxic Unit for Humans (CTUh)",
    "SimpleName": "Cancer Disease",
    "Set": "Health"
  },
  {
    "Index": 7,
    "ID": "impact potential/hncn/ctuh",
    "Name": "Human Health - Noncancer",
    "Code": "HNCN",
    "Unit": "CTUh",
    "Group": "Impact Potential",
    "SimpleUnit": "Comparative Toxic Unit for Humans (CTUh)",
    "SimpleName": "Noncancer Disease",
    "Set": "Health"
  },
  {
    "Index": 8,
    "ID": "impact potential/htox/ctuh",
    "Name": "Human Health Toxicity",
    "Code": "HTOX",
    "Unit": "CTUh",
    "Group": "Impact Potential",
    "SimpleUnit": "Comparative Toxic Unit for Humans (CTUh)",
    "SimpleName": "Toxic to Humans",
    "Set": "Health"
  },
  {
    "Index": 9,
    "ID": "impact potential/hrsp/kg pm2.5-eq",
    "Name": "Human Health - Respiratory Effects",
    "Code": "HRSP",
    "Unit": "kg PM2.5-eq",
    "Group": "Impact Potential",
    "SimpleUnit": "Kilograms Particulate Matter",
    "SimpleName": "Respiratory Effects",
    "Set": "Air"
  },
  {
    "Index": 10,
    "ID": "impact potential/ozon/kg cfc-11-eq",
    "Name": "Ozone Depletion",
    "Code": "OZON",
    "Unit": "kg CFC-11-eq",
    "Group": "Impact Potential",
    "SimpleUnit": "Kilograms ChloroFluoroCarbon-11",
    "SimpleName": "Ozone Depletion",
    "Set": "Air"
  },
  {
    "Index": 11,
    "ID": "impact potential/smog/kg o3-eq",
    "Name": "Smog Formation",
    "Code": "SMOG",
    "Unit": "kg O3-eq",
    "Group": "Impact Potential",
    "SimpleUnit": "Kilograms Ozone (O3)",
    "SimpleName": "Smog Formation",
    "Set": "Air"
  },
  {
    "Index": 12,
    "ID": "resource use/nnrg/mj",
    "Name": "Nonrenewable Energy Use",
    "Code": "NNRG",
    "Unit": "MJ",
    "Group": "Resource Use",
    "SimpleUnit": "Megajoules (MJ)",
    "SimpleName": "Nonrenewable Energy Use",
    "Set": "Energy"
  },
  {
    "Index": 13,
    "ID": "resource use/rnrg/mj",
    "Name": "Renewable Energy Use",
    "Code": "RNRG",
    "Unit": "MJ",
    "Group": "Resource Use",
    "SimpleUnit": "Megajoules (MJ)",
    "SimpleName": "Renewable Energy Use",
    "Set": "Energy"
  },
  {
    "Index": 14,
    "ID": "resource use/enrg/mj",
    "Name": "Energy Use",
    "Code": "ENRG",
    "Unit": "MJ",
    "Group": "Resource Use",
    "SimpleUnit": "Megajoules (MJ)",
    "SimpleName": "Energy Use",
    "Set": "Energy"
  },
  {
    "Index": 15,
    "ID": "resource use/land/m2*yr",
    "Name": "Land Use",
    "Code": "LAND",
    "Unit": "m2*yr",
    "Group": "Resource Use",
    "SimpleUnit": "Square Meters per Year",
    "SimpleName": "Land Use",
    "Set": "Land"
  },
  {
    "Index": 16,
    "ID": "resource use/watr/m3",
    "Name": "Water Use",
    "Code": "WATR",
    "Unit": "m3",
    "Group": "Resource Use",
    "SimpleUnit": "Cubic Meters",
    "SimpleName": "Water Use",
    "Set": "Water"
  },
  {
    "Index": 17,
    "ID": "resource use/mnrl/kg",
    "Name": "Minerals and Metals Use",
    "Code": "MNRL",
    "Unit": "kg",
    "Group": "Resource Use",
    "SimpleUnit": "Kilograms",
    "SimpleName": "Minerals and Metals Use",
    "Set": "Land"
  },
  {
    "Index": 18,
    "ID": "chemical releases/pest/kg",
    "Name": "Pesticides",
    "Code": "PEST",
    "Unit": "kg",
    "Group": "Chemical Releases",
    "SimpleUnit": "Kilograms",
    "SimpleName": "Pesticides",
    "Set": "Land"
  },
  {
    "Index": 19,
    "ID": "chemical releases/metl/kg",
    "Name": "Metals",
    "Code": "METL",
    "Unit": "kg",
    "Group": "Chemical Releases",
    "SimpleUnit": "Kilograms",
    "SimpleName": "Metals",
    "Set": "Land"
  },
  {
    "Index": 20,
    "ID": "chemical releases/haps/kg",
    "Name": "Hazardous Air Pollutants",
    "Code": "HAPS",
    "Unit": "kg",
    "Group": "Chemical Releases",
    "SimpleUnit": "Kilograms",
    "SimpleName": "Hazardous Air Pollutants",
    "Set": "Air"
  },
  {
    "Index": 21,
    "ID": "economic & social/vadd/$",
    "Name": "Value Added",
    "Code": "VADD",
    "Unit": "$",
    "Group": "Economic & Social",
    "SimpleUnit": "US Dollars ($)",
    "SimpleName": "Value Added",
    "Set": "Wealth"
  },
  {
    "Index": 22,
    "ID": "economic & social/jobs/jobs",
    "Name": "Jobs Supported",
    "Code": "JOBS",
    "Unit": "jobs",
    "Group": "Economic & Social",
    "SimpleUnit": "Employees",
    "SimpleName": "Jobs Supported",
    "Set": "Wealth"
  },
  {
    "Index": 23,
    "ID": "waste generated/crhw/kg",
    "Name": "Commercial RCRA Hazardous Waste",
    "Code": "CRHW",
    "Unit": "kg",
    "Group": "Waste Generated",
    "SimpleUnit": "Kilograms",
    "SimpleName": "Hazardous Waste",
    "Set": "Land"
  },
  {
    "Index": 24,
    "ID": "waste generated/cmsw/kg",
    "Name": "Commercial Municipal Solid Waste",
    "Code": "CMSW",
    "Unit": "kg",
    "Group": "Waste Generated",
    "SimpleUnit": "Kilograms",
    "SimpleName": "Municipal Solid Waste",
    "Set": "Land"
  },
  {
    "Index": 25,
    "ID": "waste generated/fmsw/kg",
    "Name": "Food in Commercial Municipal Solid Waste",
    "Code": "FMSW",
    "Unit": "kg",
    "Group": "Waste Generated",
    "SimpleUnit": "Kilograms",
    "SimpleName": "Food Waste",
    "Set": "Land"
  },
  {
    "Index": 26,
    "ID": "waste generated/ccdd/kg",
    "Name": "Commercial Construction and Demolition Debris",
    "Code": "CCDD",
    "Unit": "kg",
    "Group": "Waste Generated",
    "SimpleUnit": "Kilograms",
    "SimpleName": "Construction Debris",
    "Set": "Land"
  }
]
